[{
        "title": "Mango People Jacket",
        "price": "$52.00",
        "imgsrc": "img/product_img_1.png"
    },
    {
        "title": "Mango People Coat",
        "price": "$52.00",
        "imgsrc": "img/product_img_2.png"
    },
    {
        "title": "Mango People Jacket",
        "price": "$52.00",
        "imgsrc": "img/product_img_3.png"
    },
    {
        "title": "Mango People T-shirt",
        "price": "$52.00",
        "imgsrc": "img/product_img_4.png"
    },
    {
        "title": "Mango People Hoodie",
        "price": "$52.00",
        "imgsrc": "img/product_img_5.png"
    },
    {
        "title": "Mango People Tunic",
        "price": "$52.00",
        "imgsrc": "img/product_img_6.png"
    },
    {
        "title": "Mango People Suit",
        "price": "$52.00",
        "imgsrc": "img/product_img_7.png"
    },
    {
        "title": "Mango People Jacket",
        "price": "$52.00",
        "imgsrc": "img/product_img_8.png"
    },
    {
        "title": "Mango People T-shirt",
        "price": "$52.00",
        "imgsrc": "img/product_img_9.png"
    }
]